parsable/__init__.py
parsable/backports.py
parsable/collection.py
parsable/main.py
regex_pypeline-0.0.21.dist-info/LICENSE
regex_pypeline-0.0.21.dist-info/METADATA
regex_pypeline-0.0.21.dist-info/WHEEL
regex_pypeline-0.0.21.dist-info/top_level.txt
regex_pypeline-0.0.21.dist-info/RECORD
